mthmr/__init__.py
mthmr/mthmr_query.py
mthmr-0.0.5.dist-info/LICENSE
mthmr-0.0.5.dist-info/METADATA
mthmr-0.0.5.dist-info/WHEEL
mthmr-0.0.5.dist-info/top_level.txt
mthmr-0.0.5.dist-info/RECORD
