Metadata-Version: 2.1
Name: mthmr
Version: 0.0.5
Summary: MTHMR CashBack Service
Home-page: 
Author: Andrey Kovalchuk
Author-email: a.kovalchuk@mthmr.com
Classifier: Programming Language :: Python :: 3
Classifier: License :: OSI Approved :: MIT License
Classifier: Operating System :: OS Independent
Requires-Python: >=3.9
License-File: LICENSE
